pypaq/__init__.py
pypaq/exception.py
pypaq/pytypes.py
pypaq/lipytools/__init__.py
pypaq/lipytools/decorators.py
pypaq/lipytools/double_hinge.py
pypaq/lipytools/files.py
pypaq/lipytools/moving_average.py
pypaq/lipytools/opt_process.py
pypaq/lipytools/plots.py
pypaq/lipytools/printout.py
pypaq/lipytools/pylogger.py
pypaq/lipytools/softmax.py
pypaq/lipytools/stats.py
pypaq/lipytools/time_reporter.py
pypaq/lipytools/valarr.py
pypaq/mpython/__init__.py
pypaq/mpython/devices.py
pypaq/mpython/mpdecor.py
pypaq/mpython/mptools.py
pypaq/pms/__init__.py
pypaq/pms/base.py
pypaq/pms/config_manager.py
pypaq/pms/para.py
pypaq/pms/parasave.py
pypaq/pms/paspa.py
pypaq/pms/points_cloud.py
pypaq/pms/space_estimator.py
pypaq/textools/__init__.py
pypaq/textools/text_metrics.py
pypaq/textools/text_processing.py
pypaq-1.16.2.dist-info/METADATA
pypaq-1.16.2.dist-info/WHEEL
pypaq-1.16.2.dist-info/top_level.txt
pypaq-1.16.2.dist-info/RECORD
