Metadata-Version: 2.1
Name: pypaq
Version: 1.16.2
Summary: little Python tools
Home-page: https://github.com/piteren/pypaq.git
Author: Piotr Niewinski
Author-email: pioniewinski@gmail.com
License: MIT
Requires-Dist: Levenshtein
Requires-Dist: matplotlib
Requires-Dist: numpy
Requires-Dist: pandas
Requires-Dist: plotly
Requires-Dist: psutil
Requires-Dist: pyyaml
Requires-Dist: scipy
Requires-Dist: scikit-learn
